flexible_content
mock_project
