Metadata-Version: 1.0
Name: django-flexible-content
Version: 0.9.1
Summary: Allows granular, typed, extensible control over a page's content.
Home-page: https://github.com/hjkelly/django-flexible-content
Author: Harrison Kelly
Author-email: hjkelly@gmail.com
License: UNKNOWN
Platform: UNKNOWN
